vcapi/vcapi.py
vcapi-1.0.1a4.dist-info/DESCRIPTION.rst
vcapi-1.0.1a4.dist-info/METADATA
vcapi-1.0.1a4.dist-info/RECORD
vcapi-1.0.1a4.dist-info/WHEEL
vcapi-1.0.1a4.dist-info/entry_points.txt
vcapi-1.0.1a4.dist-info/metadata.json
vcapi-1.0.1a4.dist-info/top_level.txt
